archeme/__init__.py
archeme/generate.py
archeme/merge.py
archeme-1.0.2.dist-info/LICENSE
archeme-1.0.2.dist-info/METADATA
archeme-1.0.2.dist-info/WHEEL
archeme-1.0.2.dist-info/entry_points.txt
archeme-1.0.2.dist-info/top_level.txt
archeme-1.0.2.dist-info/RECORD
