Metadata-Version: 2.1
Name: archeme
Version: 1.0.2
Summary: Command-line tool to describe and visualize architecture schemes.
Home-page: https://github.com/foliant-docs/archeme
Author: Artemy Lomov
Author-email: artemy@lomov.ru
License: MIT
Download-URL: https://pypi.org/project/archeme
Platform: any
Classifier: Development Status :: 5 - Production/Stable
Classifier: Environment :: Console
Classifier: Intended Audience :: Developers
Classifier: License :: OSI Approved :: MIT License
Classifier: Operating System :: OS Independent
Classifier: Programming Language :: Python
Classifier: Topic :: Documentation
Classifier: Topic :: Utilities
Classifier: Programming Language :: Python :: 3.6
Requires-Dist: PyYAML (>=5.1.1)
